qontrol.py
qontrol-1.1.1.dist-info/LICENSE
qontrol-1.1.1.dist-info/METADATA
qontrol-1.1.1.dist-info/WHEEL
qontrol-1.1.1.dist-info/top_level.txt
qontrol-1.1.1.dist-info/RECORD
