Metadata-Version: 2.1
Name: qontrol
Version: 1.1.1
Summary: Python Library for interfacing with Qontrol integrated optics control hardware.
Home-page: https://github.com/takeqontrol/api
Author: Qontrol
Author-email: support@qontrol.co.uk
License: UNKNOWN
Platform: UNKNOWN
Classifier: Programming Language :: Python :: 3
Classifier: Operating System :: OS Independent
License-File: LICENSE
Requires-Dist: pyserial
